v1/__main__.py
v1/help.py
v1/tods.py
Krish-1.0.6.dist-info/METADATA
Krish-1.0.6.dist-info/WHEEL
Krish-1.0.6.dist-info/entry_points.txt
Krish-1.0.6.dist-info/top_level.txt
Krish-1.0.6.dist-info/RECORD
