Metadata-Version: 2.1
Name: Krish
Version: 1.0.6
Summary: Meet A new A.I. - Krish
Home-page: UNKNOWN
Author: Mausam Kaushal
Author-email: tbot1738@gmail.com
License: MIT
Platform: UNKNOWN
Classifier: License :: OSI Approved :: MIT License
Classifier: Programming Language :: Python :: 3
Classifier: Programming Language :: Python :: 3.8
Requires-Dist: pyttsx3
Requires-Dist: speechrecognition
Requires-Dist: wikipedia
Requires-Dist: youtube-search-python
Requires-Dist: pafy
